starfish/__init__.py
starfish/common/env_loader.py
starfish/common/exceptions.py
starfish/common/logger.py
starfish/components/__init__.py
starfish/components/prepare_topic.py
starfish/data_factory/config.py
starfish/data_factory/constants.py
starfish/data_factory/event_loop.py
starfish/data_factory/factory.py
starfish/data_factory/factory_.py
starfish/data_factory/factory_executor_manager.py
starfish/data_factory/factory_wrapper.py
starfish/data_factory/job_manager.py
starfish/data_factory/job_manager_dry_run.py
starfish/data_factory/job_manager_re_run.py
starfish/data_factory/storage/base.py
starfish/data_factory/storage/in_memory/in_memory_storage.py
starfish/data_factory/storage/local/__init__.py
starfish/data_factory/storage/local/data_handler.py
starfish/data_factory/storage/local/local_storage.py
starfish/data_factory/storage/local/metadata_handler.py
starfish/data_factory/storage/local/setup.py
starfish/data_factory/storage/local/utils.py
starfish/data_factory/storage/models.py
starfish/data_factory/storage/registry.py
starfish/data_factory/task_runner.py
starfish/data_factory/utils/data_class.py
starfish/data_factory/utils/decorator.py
starfish/data_factory/utils/enums.py
starfish/data_factory/utils/errors.py
starfish/data_factory/utils/mock.py
starfish/data_factory/utils/state.py
starfish/data_factory/utils/util.py
starfish/data_gen_template/cli.py
starfish/data_gen_template/core.py
starfish/data_gen_template/templates/starfish/function_calling/README.md
starfish/data_gen_template/templates/starfish/function_calling/generator.py
starfish/data_gen_template/templates/starfish/function_calling/utils.py
starfish/data_gen_template/templates/starfish/generate_by_topic/generator.py
starfish/data_gen_template/templates/starfish/generate_by_topic/utils.py
starfish/data_gen_template/utils/errors.py
starfish/data_ingest/formatter/template_format.py
starfish/data_ingest/ingest.py
starfish/data_ingest/parsers/__init__.py
starfish/data_ingest/parsers/base_parser.py
starfish_core-0.1.3.dist-info/LICENSE
starfish_core-0.1.3.dist-info/METADATA
starfish_core-0.1.3.dist-info/WHEEL
starfish_core-0.1.3.dist-info/entry_points.txt
starfish_core-0.1.3.dist-info/RECORD
