Metadata-Version: 2.3
Name: starfish-core
Version: 0.1.3
Summary: 
Author: Starfish AI Inc.
Requires-Python: >=3.10,<4.0
Classifier: Programming Language :: Python :: 3
Classifier: Programming Language :: Python :: 3.10
Classifier: Programming Language :: Python :: 3.11
Classifier: Programming Language :: Python :: 3.12
Classifier: Programming Language :: Python :: 3.13
Provides-Extra: all
Provides-Extra: docx
Provides-Extra: excel
Provides-Extra: pdf
Provides-Extra: ppt
Provides-Extra: unstructured
Provides-Extra: youtube
Requires-Dist: aiofiles (>=24.1.0,<25.0.0)
Requires-Dist: aiosqlite (>=0.21.0,<0.22.0)
Requires-Dist: cachetools (>=5.5.2,<6.0.0)
Requires-Dist: cloudpickle (>=2.2.0,<3.0.0)
Requires-Dist: cryptography (>=44.0.1)
Requires-Dist: docstring_parser (>=0.16.0,<0.17.0)
Requires-Dist: litellm (>=1.65.1,<2.0.0)
Requires-Dist: loguru (>=0.7.3,<0.8.0)
Requires-Dist: mcp (>=1.8.1,<2.0.0)
Requires-Dist: nest_asyncio (>=1.6.0,<2.0.0)
Requires-Dist: ollama (>=0.4.7,<0.5.0)
Requires-Dist: openpyxl ; extra == "excel" or extra == "all"
Requires-Dist: pdfminer_six (>=20250506,<20250507) ; extra == "pdf" or extra == "all"
Requires-Dist: posthog (>=3.11.0,<4.0.0)
Requires-Dist: psutil (>=7.0.0,<8.0.0)
Requires-Dist: python-docx ; extra == "docx" or extra == "all"
Requires-Dist: python-dotenv (>=1.1.0,<2.0.0)
Requires-Dist: python-pptx ; extra == "ppt" or extra == "all"
Requires-Dist: pytube (>=15.0.0,<16.0.0) ; extra == "youtube" or extra == "all"
Requires-Dist: typing-extensions (>=4.0.0,<5.0.0)
Requires-Dist: unstructured[pdf] (>=0.10.0,<0.11.0) ; extra == "unstructured" or extra == "all"
Requires-Dist: youtube-transcript-api (>=0.6.1,<0.7.0) ; extra == "youtube" or extra == "all"
